place/__init__.py
place/tools/__init__.py
place/tools/place_api_tool.py
place/tools/utils.py
place/yamls/place_api_tool.yaml
tests/__init__.py
tests/test_place_api_tool.py
place_api_test-0.1.8.dist-info/METADATA
place_api_test-0.1.8.dist-info/WHEEL
place_api_test-0.1.8.dist-info/entry_points.txt
place_api_test-0.1.8.dist-info/top_level.txt
place_api_test-0.1.8.dist-info/RECORD
