Metadata-Version: 2.1
Name: place_api_test
Version: 0.1.8
Summary: This is my tools package
